Metadata-Version: 2.1
Name: my_datetime_project
Version: 0.1.2
Summary: A simple Python project to print current date and time
Author-email: zhouyx <zhouyx.100@gmail.com>
